[
  {
    "meta": {
      "promoId": "PRM-20251002-173002-001-SXED",
      "title": null,
      "type": "storefront",
      "version": 1,
      "links": {
        "userId": null,
        "merchantId": "MRC-20251002-170602-401-ASDF"
      },
      "status": {
        "isActive": true,
        "priority": 1,
        "visibility": "public"
      },
      "schedule": {
      "start": "2025-07-22T00:00:00Z",
      "end": "2025-07-29T23:59:59Z"
      },
      "createdAt": "2025-08-04T12:00:00Z",
      "updatedAt": "2025-08-04T12:00:00Z"
    },
    "display": {
      "banner": {
        "type": "AD",
        "title": "Affordable groceries & fast internet!",
        "subtitle": "Limited time promotion for our best-selling merchant!",
        "imageUrl": "/promotions/banners/icg-banner.jpg",
        "priceText": "Shop Now!"
      },
      "brand": {
        "logoUrl": "../source/assets/logos/app-logo.png",
        "name": "mStore",
        "itemBrandText": "New Arrivals"
      },
      "action": {
        "type": "LINK",
        "value": "#",
        "ctaText": "Explore ➔"
      },
      "notification": {
        "enabled": true,
        "title": "Promotion Time!",
        "message": "🔥 Exclusive offers from Internet Cafe & Grocery!",
        "type": "info",
        "icon": "fas fa-bullhorn"
      }
    },
    "targeting": {
      "locations": [],
      "userGroups": [],
      "platforms": [
        "web",
        "android",
        "ios",
        "desktop"
      ]
    },
    "rules": {
      "minOrderValue": 0,
      "maxUsagePerUser": null,
      "applicableItems": {
        "type": "include",
        "itemIds": [],
        "categoryIds": []
      }
    },
    "reward": {
      "type": "fixed_discount",
      "value": {
        "amount": 0
      },
      "description": "",
      "couponCode": null
    },
    "ui_overrides": {
      "header": {
        "backgroundColor": "#FF5733",
        "textColor": "#ffffff",
        "logo": "/admin/assets/images/merchants/logo/icg-logo.jpg",
        "title": "Internet Cafe & Grocery"
      },
      "bottomNav": [
        {
          "label": "Home",
          "icon": "fas fa-home",
          "link": "/merchant/MRC-20251002-170602-401-ASDF"
        },
        {
          "label": "Chat",
          "icon": "fas fa-comment-dots",
          "link": "/merchant/MRC-20251002-170602-401-ASDF/chat"
        },
        {
          "label": "Saved",
          "icon": "fas fa-heart",
          "link": "/merchant/MRC-20251002-170602-401-ASDF/saved"
        },
        {
          "label": "Cart",
          "icon": "fas fa-shopping-cart",
          "link": "/merchant/MRC-20251002-170602-401-ASDF/cart"
        },
        {
          "label": "Profile",
          "icon": "fas fa-user",
          "link": "/merchant/MRC-20251002-170602-401-ASDF/profile"
        }
      ]
    },
    "analytics": {
      "views": 0,
      "clicks": 0,
      "conversions": 0
    }
  },
  {
    "meta": {
      "promoId": "PRM-20251002-173003-002-CFRV",
      "type": "banner",
      "version": 1,
      "links": {
        "userId": null,
        "merchantId": null
      },
      "status": {
        "isActive": true,
        "priority": 1,
        "visibility": "public"
      },
      "schedule": {
        "start": "2025-09-05T00:00:00Z",
        "end": "2027-07-29T23:59:59Z"
      },
      "createdAt": "2025-08-04T12:00:00Z",
      "updatedAt": "2025-08-04T12:00:00Z"
    },
    "display": {
      "banner": {
        "type": "AD",
        "title": "Fresh Stock Daily!",
        "subtitle": "Discover the latest products at amazing prices.",
        "imageUrl": "./localstore/images/items/red-bull.jpg",
        "priceText": "Shop Now!"
      },
      "brand": {
        "logoUrl": "./source/assets/logos/app-logo.png",
        "name": "mStore",
        "itemBrandText": "New Arrivals"
      },
      "action": {
        "type": "LINK",
        "value": "#",
        "ctaText": "Explore ➔"
      }
    }
  },
  {
    "meta": {
      "promoId": "PRM-20251002-173004-003-TGBH",
      "type": "banner",
      "version": 1,
      "links": {
        "userId": null,
        "merchantId": null
      },
      "status": {
        "isActive": true,
        "priority": 1,
        "visibility": "public"
      },
      "schedule": {
        "start": "2025-09-01T00:00:00Z",
        "end": "2027-09-30T23:59:59Z"
      },
      "createdAt": "2025-09-06T10:00:00Z",
      "updatedAt": "2025-09-06T10:00:00Z"
    },
    "display": {
      "banner": {
        "type": "INFO",
        "title": "Limited Time Offer!",
        "subtitle": "Get 20% off on all electronics.",
        "imageUrl": "./localstore/images/items/colgate-paste.jpg",
        "priceText": "Grab it now!"
      },
      "brand": {
        "logoUrl": "./source/assets/logos/app-logo.png",
        "name": "mStore",
        "itemBrandText": "Special Deal"
      },
      "action": {
        "type": "LINK",
        "value": "#",
        "ctaText": "View Details ➔"
      }
    }
  },
  {
    "meta": {
      "promoId": "PRM-20251002-173005-004-YJNM",
      "type": "banner",
      "version": 1,
      "links": {
        "userId": null,
        "merchantId": null
      },
      "status": {
        "isActive": true,
        "priority": 1,
        "visibility": "public"
      },
      "schedule": {
        "start": "2025-09-01T00:00:00Z",
        "end": "2027-09-30T23:59:59Z"
      },
      "createdAt": "2025-09-06T10:05:00Z",
      "updatedAt": "2025-09-06T10:05:00Z"
    },
    "display": {
      "banner": {
        "type": "AD",
        "title": "New Arrivals in Fashion!",
        "subtitle": "Explore our trendy collection.",
        "imageUrl": "./localstore/images/items/lux-soap.jpg",
        "priceText": "Shop Fashion"
      },
      "brand": {
        "logoUrl": "./source/assets/logos/app-logo.png",
        "name": "mStore",
        "itemBrandText": "Fashion"
      },
      "action": {
        "type": "LINK",
        "value": "#",
        "ctaText": "Browse Now ➔"
      }
    }
  },
  {
    "meta": {
      "promoId": "PRM-20251002-173006-005-UKIL",
      "title": null,
      "type": "banner",
      "version": 1,
      "links": {
        "userId": null,
        "merchantId": null
      },
      "status": {
        "isActive": true,
        "priority": 1,
        "visibility": "public"
      },
      "schedule": {
        "start": "2025-09-01T00:00:00Z",
        "end": "2027-09-30T23:59:59Z"
      },
      "createdAt": "2025-09-06T11:00:00Z",
      "updatedAt": "2025-09-06T11:00:00Z"
    },
    "display": {
      "banner": {
        "type": "INFO",
        "title": "Grand Opening Sale!",
        "subtitle": "Up to 50% off on all items for a limited time. Don't miss out!",
        "imageUrl": "./localstore/images/items/kurkure.jpg",
        "priceText": "Shop Now"
      },
      "brand": {
        "logoUrl": "./source/assets/logos/app-logo.png",
        "name": "mStore",
        "itemBrandText": "New Store"
      },
      "action": {
        "type": "LINK",
        "value": "#",
        "ctaText": "Visit Store ➔"
      }
    }
  },
  {
    "meta": {
      "promoId": "PRM-20251002-173007-006-OLPK",
      "title": null,
      "type": "banner",
      "version": 1,
      "links": {
        "userId": null,
        "merchantId": null
      },
      "status": {
        "isActive": true,
        "priority": 1,
        "visibility": "public"
      },
      "schedule": {
        "start": "2025-09-01T00:00:00Z",
        "end": "2027-09-30T23:59:59Z"
      },
      "createdAt": "2025-09-06T11:05:00Z",
      "updatedAt": "2025-09-06T11:05:00Z"
    },
    "display": {
      "banner": {
        "type": "AD",
        "title": "Fresh Produce Arrived!",
        "subtitle": "Organic fruits and vegetables, directly from local farms. Healthy and delicious!",
        "imageUrl": "./localstore/images/items/rice.jpg",
        "priceText": "Order Fresh"
      },
      "brand": {
        "logoUrl": "./source/assets/logos/app-logo.png",
        "name": "mStore",
        "itemBrandText": "Farm Fresh"
      },
      "action": {
        "type": "LINK",
        "value": "#",
        "ctaText": "View Produce ➔"
      }
    }
  }
]